RoboFlowSocket/RoboFlowSocketSDK.py
RoboFlowSocket/__init__.py
RoboFlowSocket-1.0.dist-info/LICENSE
RoboFlowSocket-1.0.dist-info/METADATA
RoboFlowSocket-1.0.dist-info/WHEEL
RoboFlowSocket-1.0.dist-info/top_level.txt
RoboFlowSocket-1.0.dist-info/RECORD
